snv_feast/__init__.py
snv_feast/snv_feast.py
snv_feast/snv_feast_cli.py
snv_feast/helpers/__init__.py
snv_feast/helpers/helpers.py
SNV_FEAST-0.0.8.dist-info/LICENSE.txt
SNV_FEAST-0.0.8.dist-info/METADATA
SNV_FEAST-0.0.8.dist-info/WHEEL
SNV_FEAST-0.0.8.dist-info/top_level.txt
SNV_FEAST-0.0.8.dist-info/RECORD
