Metadata-Version: 2.1
Name: SNV-FEAST
Version: 0.0.8
Summary: A package to get signature SNVs from a given strain and set of sink and sources, using MIDAS output
Author-email: "Leah Briscoe, Eran Halperin, Nandita Garud" <leahpbriscoe@gmail.com>
Project-URL: Homepage, https://github.com/garudlab/SNV-FEAST
Project-URL: Bug Tracker, https://github.com/garudlab/SNV-FEAST/issues
Classifier: Programming Language :: Python :: 3
Classifier: License :: OSI Approved :: MIT License
Classifier: Operating System :: OS Independent
Requires-Python: >=3.0
License-File: LICENSE.txt
Requires-Dist: numpy (>=1.20.3)
Requires-Dist: scipy (>=1.7.1)
Requires-Dist: pyyaml (>=6.0)
Requires-Dist: pandas (>=1.3.4)
Requires-Dist: bz2file (>=0.98)
